howcani/__init__.py
howcani/cache.py
howcani/howcani.py
howcani/utility.py
howcani/plugins/Plugin.py
howcani/plugins/__init__.py
howcani/plugins/stackoverflow.py
howcani-0.0.1.dist-info/LICENSE
howcani-0.0.1.dist-info/METADATA
howcani-0.0.1.dist-info/WHEEL
howcani-0.0.1.dist-info/entry_points.txt
howcani-0.0.1.dist-info/top_level.txt
howcani-0.0.1.dist-info/RECORD
