Metadata-Version: 2.1
Name: howcani
Version: 0.0.1
Summary: CLI Query Searcher
Home-page: https://github.com/rahuldshetty/howcani
Author: Rahul D Shetty
Author-email: 35rahuldshetty@gmail.com
License: MIT
Keywords: rahuldshetty howcani search stackoverflow google
Platform: UNKNOWN
Classifier: Programming Language :: Python :: 3
Classifier: License :: OSI Approved :: MIT License
Classifier: Operating System :: OS Independent
Requires-Dist: requests
Requires-Dist: beautifulsoup4 (==4.9.3)
Requires-Dist: google
